<?xml version="1.0" encoding="UTF-8"?>
<PE_PROJECT_SETTINGS_DOCUMENTATION>
  <PE_product_version v="version 10.3 for Freescale Microcontrollers" />
  <PE_core_version v="Processor Expert Version 0508" />
  <CPU_Bean name="Cpu" type="MKL25Z128LH4">
    <Enabled v="Y" />
    <Properties>
      <Component_name v="Cpu" />
      <CPU_type v="MKL25Z128VLH4" />
      <list name="Shared Internal properties" v="1">
        <EmptySection_DummyValue />
      </list>
      <list name="Shared Clock settings" v="1">
        <group name="Clock settings">
          <group name="Internal oscillator">
            <Slow_internal_reference_clock__kHz_ v="32.768000000000" />
            <boolgroup name="Initialize slow trim value" v="no" />
            <Fast_internal_reference_clock__MHz_ v="4" />
            <boolgroup name="Initialize fast trim value" v="no" />
          </group>
          <boolgroup name="RTC clock input" v="Disabled" />
          <boolgroup name="System oscillator 0" v="Enabled">
            <enumgroup name="Clock source" v="External crystal">
              <group name="Clock input pin">
                <Pin_name v="EXTAL0/PTA18/UART1_RX/TPM_CLKIN0" />
                <Pin_signal v="EXTAL" />
              </group>
              <group name="Clock output pin">
                <Pin_name v="XTAL0/PTA19/UART1_TX/TPM_CLKIN1/LPTMR0_ALT1" />
                <Pin_signal v="XTAL" />
              </group>
              <Clock_frequency__MHz_ v="8" />
              <Capacitor_load v="18pF" />
              <Oscillator_operating_mode v="Low power" />
            </enumgroup>
          </boolgroup>
          <list name="Clock source settings" v="1">
            <group name="Clock source setting 0">
              <group name="Internal reference clock">
                <MCGIRCLK_clock v="Enabled" />
                <MCGIRCLK_in_stop v="Disabled" />
                <enumgroup name="MCGIRCLK source" v="Slow">
                  <EmptySection_DummyValue />
                </enumgroup>
                <MCGIRCLK_clock__MHz_ v="0.032768000000" />
              </group>
              <group name="External reference clock">
                <OSC0ERCLK_clock v="Enabled" />
                <OSC0ERCLK_in_stop v="Disabled" />
                <OSC0ERCLK_clock__MHz_ v="8" />
                <ERCLK32K_clock_source v="Auto select" />
                <ERCLK32K__clock__MHz_ v="0.001000000000" />
              </group>
              <group name="MCG settings">
                <enumgroup name="MCG mode" v="PEE">
                  <EmptySection_DummyValue />
                </enumgroup>
                <MCG_output_clock v="PLL clock" />
                <MCG_output__MHz_ v="96" />
                <MCG_external_ref__clock__MHz_ v="8" />
                <Clock_monitor v="Disabled" />
                <group name="FLL settings">
                  <FLL_module v="Disabled" />
                  <FLL_output__MHz_ v="0" />
                  <MCGFFCLK_clock__kHz_ v="15.625000000000" />
                  <enumgroup name="Reference clock source" v="External clock">
                    <Reference_clock_divider v="Auto select" />
                  </enumgroup>
                  <FLL_reference_clock__kHz_ v="31.250000000000" />
                  <Multiplication_factor v="Auto select" />
                </group>
                <group name="PLL 0 settings">
                  <PLL_module v="Enabled" />
                  <PLL_module_in_Stop v="Disabled" />
                  <PLL_output__MHz_ v="96" />
                  <Reference_clock_divider v="Auto select" />
                  <PLL_reference_clock__MHz_ v="4" />
                  <Multiplication_factor v="Auto select" />
                  <Loss_of_lock_interrupt v="Disabled" />
                </group>
              </group>
            </group>
          </list>
        </group>
      </list>
      <Initialization_priority v="interrupts enabled" />
      <Watchdog_disable v="yes" />
      <group name="Internal peripherals">
        <list name="Shared NMI settings" v="1">
          <boolgroup name="NMI pin" v="Enabled">
            <NMI_Pin v="TSI0_CH5/PTA4/I2C1_SDA/TPM0_CH1/NMI_b" />
            <NMI_Pin_signal v="" />
          </boolgroup>
        </list>
        <list name="Shared Reset settings" v="1">
          <boolgroup name="Reset control" v="Enabled">
            <Reset_pin v="PTA20/RESET_b" />
            <Reset_pin_signal v="" />
            <Filter_in_STOP v="Disabled" />
            <Filter_in_RUN_WAIT v="Disabled" />
            <Filter_width v="1" />
          </boolgroup>
        </list>
        <list name="Shared Flash memory organization" v="1">
          <group name="Flash memory organization">
            <list name="Shared FLASH settings" v="1">
              <EmptySection_DummyValue />
            </list>
            <list name="Flash blocks" v="1">
              <group name="Flash block 0">
                <Address v="0" />
                <Size v="131072" />
                <Write_unit_size v="4" />
                <Erase_unit_size v="1024" />
                <Protection_unit_size v="4096" />
              </group>
            </list>
          </group>
        </list>
        <list name="Shared Flash Config settings" v="1">
          <boolgroup name="Flash configuration field" v="Enabled">
            <group name="Security settings">
              <Flash_security v="Disabled" />
              <Freescale_failure_analysis_access v="Enabled" />
              <Mass_erase v="Enabled" />
              <Backdoor_key_security v="Disabled" />
              <Backdoor_key_0 v="255" />
              <Backdoor_key_1 v="255" />
              <Backdoor_key_2 v="255" />
              <Backdoor_key_3 v="255" />
              <Backdoor_key_4 v="255" />
              <Backdoor_key_5 v="255" />
              <Backdoor_key_6 v="255" />
              <Backdoor_key_7 v="255" />
            </group>
            <group name="Protection regions">
              <group name="P-Flash protection settings">
                <Protection_region_size v="4096" />
                <P_Flash_protection v="4294967295" />
                <group name="Protection regions">
                  <Protection_region_0 v="Unprotected" />
                  <Protection_region_1 v="Unprotected" />
                  <Protection_region_2 v="Unprotected" />
                  <Protection_region_3 v="Unprotected" />
                  <Protection_region_4 v="Unprotected" />
                  <Protection_region_5 v="Unprotected" />
                  <Protection_region_6 v="Unprotected" />
                  <Protection_region_7 v="Unprotected" />
                  <Protection_region_8 v="Unprotected" />
                  <Protection_region_9 v="Unprotected" />
                  <Protection_region_10 v="Unprotected" />
                  <Protection_region_11 v="Unprotected" />
                  <Protection_region_12 v="Unprotected" />
                  <Protection_region_13 v="Unprotected" />
                  <Protection_region_14 v="Unprotected" />
                  <Protection_region_15 v="Unprotected" />
                  <Protection_region_16 v="Unprotected" />
                  <Protection_region_17 v="Unprotected" />
                  <Protection_region_18 v="Unprotected" />
                  <Protection_region_19 v="Unprotected" />
                  <Protection_region_20 v="Unprotected" />
                  <Protection_region_21 v="Unprotected" />
                  <Protection_region_22 v="Unprotected" />
                  <Protection_region_23 v="Unprotected" />
                  <Protection_region_24 v="Unprotected" />
                  <Protection_region_25 v="Unprotected" />
                  <Protection_region_26 v="Unprotected" />
                  <Protection_region_27 v="Unprotected" />
                  <Protection_region_28 v="Unprotected" />
                  <Protection_region_29 v="Unprotected" />
                  <Protection_region_30 v="Unprotected" />
                  <Protection_region_31 v="Unprotected" />
                </group>
              </group>
            </group>
            <group name="Peripheral settings">
              <Reset_pin_function v="Enabled" />
              <NMI_function v="Enabled" />
              <FLASH_initialization_speed v="Fast" />
              <Clock_dividers_settings v="Fast clock boot" />
            </group>
          </boolgroup>
        </list>
        <list name="Shared Peripheral Bridge MCM settings" v="1">
          <boolgroup name="MCM settings" v="Disabled" />
        </list>
        <list name="Shared Power Management Controller settings" v="1">
          <group name="Power management controller">
            <LVD_reset v="Enabled" />
            <LVD_voltage_treshold v="Low" />
            <LVW_voltage_treshold v="Low" />
            <Bandgap_buffer v="Disabled" />
            <Bandgap_buffer_in_VLPx v="Disabled" />
            <group name="LVD interrupt">
              <Interrupt v="INT_LVD_LVW" />
              <Interrupt_request v="Disabled" />
              <Interrupt_priority v="0 (Highest)" />
              <LVD_interrupt v="Disabled" />
              <LVW_interrupt v="Disabled" />
            </group>
          </group>
        </list>
        <list name="Shared ClockGate settings" v="1">
          <group name="System Integration Module">
            <boolgroup name="CLKOUT pin control" v="Disabled" />
            <boolgroup name="Clock gating control" v="Disabled" />
          </group>
        </list>
      </group>
      <list name="Shared CPU interrupts/resets" v="1">
        <group name="CPU interrupts/resets">
          <boolgroup name="NMI interrupt" v="Enabled">
            <Interrupt v="INT_NMI" />
          </boolgroup>
          <boolgroup name="Hard Fault" v="Disabled" />
          <boolgroup name="Bus Fault" v="Disabled" />
          <boolgroup name="Usage Fault" v="Disabled" />
          <boolgroup name="Supervisor Call" v="Disabled" />
          <boolgroup name="Pendable Service" v="Disabled" />
          <boolgroup name="MCG Loss of lock" v="Disabled" />
        </group>
      </list>
      <group name="Low power mode settings">
        <list name="Shared Low Power Settings" v="1">
          <group name="Allowed low power modes">
            <Very_low_power_modes v="Not allowed" />
            <Low_leakage_stop_mode v="Not allowed" />
            <Very_low_leakage_stop_mode v="Not allowed" />
          </group>
        </list>
        <list name="Shared LLWU settings" v="1">
          <boolgroup name="LLWU settings" v="Disabled" />
        </list>
        <list name="Shared Low Power Settings" v="1">
          <group name="Operation mode settings">
            <group name="WAIT operation mode">
              <Return_to_wait_after_ISR v="no" />
            </group>
            <group name="SLEEP operation mode">
              <Low_Power_mode v="STOP" />
              <Return_to_stop_after_ISR v="no" />
            </group>
            <boolgroup name="STOP operation mode" v="Disabled" />
          </group>
        </list>
      </group>
      <list name="Clock configurations" v="1">
        <group name="Clock configuration 0">
          <boolgroup name="Very low power mode" v="Disabled" />
          <enumgroup name="Clock source setting" v="configuration 0">
            <MCG_mode v="PEE" />
            <MCG_output__MHz_ v="96" />
            <MCGIRCLK_clock__MHz_ v="0.032768" />
            <OSCERCLK_clock__MHz_ v="8" />
            <ERCLK32K__clock__MHz_ v="0.001" />
            <MCGFFCLK__kHz_ v="15.625" />
          </enumgroup>
          <group name="System clocks">
            <Core_clock_prescaler v="2" />
            <Core_clock v="48" />
            <Bus_clock_prescaler v="2" />
            <Bus_clock v="24" />
            <enumgroup name="PLL/FLL clock selection" v="Auto select">
              <Clock_frequency__MHz_ v="48" />
            </enumgroup>
            <enumgroup name="TPM clock selection" v="Auto select">
              <Clock_frequency__MHz_ v="48" />
            </enumgroup>
          </group>
        </group>
      </list>
    </Properties>
    <Methods>
      <list name="CPUCond" v="1">
        <SetClockConfiguration v="don&amp;apos;t generate code" />
        <GetClockConfiguration v="don&amp;apos;t generate code" />
        <SetOperationMode v="don&amp;apos;t generate code" />
        <EnableInt v="don&amp;apos;t generate code" />
        <DisableInt v="don&amp;apos;t generate code" />
        <GetLLSWakeUpFlags v="don&amp;apos;t generate code" />
        <MCGAutoTrim v="don&amp;apos;t generate code" />
        <VLPModeEnable v="don&amp;apos;t generate code" />
        <VLPModeDisable v="don&amp;apos;t generate code" />
        <SystemReset v="don&amp;apos;t generate code" />
      </list>
    </Methods>
    <Events>
      <Event_module_name v="Events" />
      <list name="EvntsShrdGrp" v="1">
        <event name="OnReset" v="don&amp;apos;t generate code" />
        <event name="OnNMIINT" v="generate code">
          <Event_procedure_name v="Cpu_OnNMIINT" />
        </event>
        <event name="OnHardFault" v="don&amp;apos;t generate code" />
        <event name="OnBusFault" v="don&amp;apos;t generate code" />
        <event name="OnUsageFault" v="don&amp;apos;t generate code" />
        <event name="OnSupervisorCall" v="don&amp;apos;t generate code" />
        <event name="OnPendableService" v="don&amp;apos;t generate code" />
        <event name="OnLossOfLockINT" v="don&amp;apos;t generate code" />
        <event name="OnLowVoltageINT" v="don&amp;apos;t generate code" />
        <event name="OnLLSWakeUpINT" v="don&amp;apos;t generate code" />
      </list>
    </Events>
    <Compiler v="GNU C Compiler" />
    <CompilerProperties>
      <Compiler v="GNU C Compiler" />
      <enumgroup name="Unhandled vectors" v="Own handler for every">
        <Unhandled_int_code>
          <StrgList><![CDATA[/* This code can be changed using the CPU component property "Build Options / Unhandled int code" */
PE_DEBUGHALT();
]]></StrgList>
        </Unhandled_int_code>
      </enumgroup>
      <group name="User initialization">
        <User_data_declarations>
          <StrgList></StrgList>
        </User_data_declarations>
        <User_code_before_PE_initialization>
          <StrgList></StrgList>
        </User_code_before_PE_initialization>
        <User_code_after_PE_initialization>
          <StrgList></StrgList>
        </User_code_after_PE_initialization>
      </group>
      <boolgroup name="Generate debugger files" v="yes">
        <Generate_mem_file v="yes" />
      </boolgroup>
      <group name="Startup">
        <Add_startup_file v="no" />
      </group>
      <boolgroup name="Generate linker file" v="yes">
        <Stack_size v="512" />
        <Heap_size v="512" />
        <Set_memory_segments_to_default v="Click to set default &amp;gt;" />
        <Default_memory_for_interrupts v="INTERNAL FLASH" />
        <Default_memory_for_code v="INTERNAL FLASH" />
        <Default_memory_for_data v="INTERNAL RAM" />
        <list name="ROM/RAM Areas" v="4">
          <group name="MemoryArea0">
            <boolgroup name="ROM/RAM Area" v="Enabled">
              <Name v="m_interrupts" />
              <Qualifier v="RX" />
              <Address v="0" />
              <Size v="192" />
            </boolgroup>
          </group>
          <group name="MemoryArea1">
            <boolgroup name="ROM/RAM Area" v="Enabled">
              <Name v="m_text_000000C0" />
              <Qualifier v="RX" />
              <Address v="192" />
              <Size v="832" />
            </boolgroup>
          </group>
          <group name="MemoryArea2">
            <boolgroup name="ROM/RAM Area" v="Enabled">
              <Name v="m_text" />
              <Qualifier v="RX" />
              <Address v="1040" />
              <Size v="130032" />
            </boolgroup>
          </group>
          <group name="MemoryArea3">
            <boolgroup name="ROM/RAM Area" v="Enabled">
              <Name v="m_data" />
              <Qualifier v="RW" />
              <Address v="536866816" />
              <Size v="16384" />
            </boolgroup>
          </group>
        </list>
      </boolgroup>
    </CompilerProperties>
  </CPU_Bean>
  <Bean name="SM_SPI0" type="SPIMaster_LDD">
    <Enabled v="Y" />
    <Properties>
      <Component_name v="SM_SPI0" />
      <Device v="SPI0" />
      <boolgroup name="Interrupt service/event" v="Disabled" />
      <group name="Settings">
        <boolgroup name="Input pin" v="Enabled">
          <Pin v="CMP0_IN1/PTC7/SPI0_MISO/SPI0_MOSI" />
          <Pin_signal v="SPI0_IN" />
        </boolgroup>
        <boolgroup name="Output pin" v="Enabled">
          <Pin v="CMP0_IN0/PTC6/LLWU_P10/SPI0_MOSI/EXTRG_IN/SPI0_MISO" />
          <Pin_signal v="SPI0_OUT" />
        </boolgroup>
        <group name="Clock pin">
          <Pin v="PTC5/LLWU_P9/SPI0_SCK/LPTMR0_ALT2/CMP0_OUT" />
          <Pin_signal v="SPI0_SCK" />
        </group>
        <list name="Chip select list" v="0">
          <EmptySection_DummyValue />
        </list>
        <list name="Attribute set list" v="1">
          <group name="Attribute set 0">
            <Width v="8 bits" />
            <MSB_first v="yes" />
            <Clock_polarity v="Low" />
            <Clock_phase v="Change on leading edge" />
            <Parity v="None" />
            <Chip_select_toggling v="no" />
            <Clock_rate_index v="0" />
          </group>
        </list>
        <Clock_rate v="4 MHz" />
        <HW_input_buffer_size v="1" />
        <HW_input_watermark v="1" />
        <boolgroup name="Receiver DMA" v="Disabled" />
        <HW_output_buffer_size v="1" />
        <HW_output_watermark v="1" />
        <boolgroup name="Transmitter DMA" v="Disabled" />
      </group>
      <group name="Initialization">
        <Initial_chip_select v="0" />
        <Initial_attribute_set v="0" />
        <Enabled_in_init__code v="no" />
        <list name="Auto Initialization" v="1">
          <Auto_initialization v="no" />
        </list>
        <group name="Event mask">
          <OnBlockSent v="Disabled" />
          <OnBlockReceived v="Disabled" />
          <OnError v="Disabled" />
        </group>
      </group>
      <list name="CPU clock/configuration selection (included)" v="1">
        <group name="CPU clock/configuration selection">
          <Clock_configuration_0 v="This component enabled" />
          <Clock_configuration_1 v="This component disabled" />
          <Clock_configuration_2 v="This component disabled" />
          <Clock_configuration_3 v="This component disabled" />
          <Clock_configuration_4 v="This component disabled" />
          <Clock_configuration_5 v="This component disabled" />
          <Clock_configuration_6 v="This component disabled" />
          <Clock_configuration_7 v="This component disabled" />
        </group>
      </list>
    </Properties>
    <Methods>
      <Init v="generate code" />
      <Deinit v="don&amp;apos;t generate code" />
      <Enable v="generate code" />
      <Disable v="generate code" />
      <SetEventMask v="don&amp;apos;t generate code" />
      <GetEventMask v="don&amp;apos;t generate code" />
      <SendBlock v="generate code" />
      <ReceiveBlock v="generate code" />
      <GetSentDataNum v="generate code" />
      <GetReceivedDataNum v="generate code" />
      <GetBlockSentStatus v="generate code" />
      <GetBlockReceivedStatus v="generate code" />
      <CancelBlockTransmission v="don&amp;apos;t generate code" />
      <CancelBlockReception v="don&amp;apos;t generate code" />
      <GetError v="don&amp;apos;t generate code" />
      <SelectConfiguration v="don&amp;apos;t generate code" />
      <Main v="generate code" />
      <ForceReceiver v="don&amp;apos;t generate code" />
      <GetStats v="don&amp;apos;t generate code" />
      <ClearStats v="don&amp;apos;t generate code" />
      <SetOperationMode v="don&amp;apos;t generate code" />
      <GetDriverState v="don&amp;apos;t generate code" />
      <ConnectPin v="don&amp;apos;t generate code" />
    </Methods>
    <Events>
      <Event_module_name v="Events" />
      <event name="OnBlockSent" v="don&amp;apos;t generate code" />
      <event name="OnBlockReceived" v="don&amp;apos;t generate code" />
      <event name="OnError" v="don&amp;apos;t generate code" />
    </Events>
  </Bean>
  <Bean name="SS_SPI1" type="SPISlave_LDD">
    <Enabled v="Y" />
    <Properties>
      <Component_name v="SS_SPI1" />
      <Device v="SPI1" />
      <boolgroup name="Interrupt service/event" v="Disabled" />
      <group name="Settings">
        <boolgroup name="Input pin" v="Enabled">
          <Pin v="ADC0_SE7b/PTD6/LLWU_P15/SPI1_MOSI/UART0_RX/SPI1_MISO" />
          <Pin_signal v="SPI1_IN" />
        </boolgroup>
        <boolgroup name="Output pin" v="Enabled">
          <Pin v="PTD7/SPI1_MISO/UART0_TX/SPI1_MOSI" />
          <Pin_signal v="SPI1_OUT" />
        </boolgroup>
        <group name="Clock pin">
          <Pin v="ADC0_SE6b/PTD5/SPI1_SCK/UART2_TX/TPM0_CH5" />
          <Pin_signal v="SPI1_SCK" />
        </group>
        <group name="Slave select">
          <Pin v="PTD4/LLWU_P14/SPI1_PCS0/UART2_RX/TPM0_CH4" />
          <Pin_signal v="SPI1_CS" />
          <Active_level v="Low" />
        </group>
        <group name="Attribute set">
          <Width v="8 bits" />
          <MSB_first v="yes" />
          <Clock_polarity v="Low" />
          <Clock_phase v="Change on leading edge" />
          <Parity v="None" />
        </group>
        <HW_input_buffer_size v="1" />
        <HW_input_watermark v="1" />
        <boolgroup name="Receiver DMA" v="Disabled" />
        <HW_output_buffer_size v="1" />
        <HW_output_watermark v="1" />
        <boolgroup name="Transmitter DMA" v="Disabled" />
      </group>
      <group name="Initialization">
        <Enabled_in_init__code v="no" />
        <list name="Auto Initialization" v="1">
          <Auto_initialization v="no" />
        </list>
        <group name="Event mask">
          <OnBlockSent v="Disabled" />
          <OnBlockReceived v="Disabled" />
          <OnError v="Disabled" />
        </group>
      </group>
    </Properties>
    <Methods>
      <Init v="generate code" />
      <Deinit v="don&amp;apos;t generate code" />
      <Enable v="generate code" />
      <Disable v="generate code" />
      <SetEventMask v="don&amp;apos;t generate code" />
      <GetEventMask v="don&amp;apos;t generate code" />
      <SendBlock v="don&amp;apos;t generate code" />
      <ReceiveBlock v="don&amp;apos;t generate code" />
      <GetSentDataNum v="don&amp;apos;t generate code" />
      <GetReceivedDataNum v="don&amp;apos;t generate code" />
      <GetBlockSentStatus v="don&amp;apos;t generate code" />
      <GetBlockReceivedStatus v="don&amp;apos;t generate code" />
      <CancelBlockTransmission v="don&amp;apos;t generate code" />
      <CancelBlockReception v="don&amp;apos;t generate code" />
      <GetError v="don&amp;apos;t generate code" />
      <Main v="generate code" />
      <ForceReceiver v="don&amp;apos;t generate code" />
      <GetStats v="don&amp;apos;t generate code" />
      <ClearStats v="don&amp;apos;t generate code" />
      <SetOperationMode v="don&amp;apos;t generate code" />
      <GetDriverState v="don&amp;apos;t generate code" />
      <ConnectPin v="don&amp;apos;t generate code" />
    </Methods>
    <Events>
      <Event_module_name v="Events" />
      <event name="OnBlockSent" v="don&amp;apos;t generate code" />
      <event name="OnBlockReceived" v="don&amp;apos;t generate code" />
      <event name="OnError" v="don&amp;apos;t generate code" />
    </Events>
  </Bean>
  <Bean name="SysTick" type="Init_SysTick">
    <Enabled v="Y" />
    <Properties>
      <Component_name v="SysTick" />
      <Device v="SysTick" />
      <group name="Settings">
        <Clock_source v="External clock" />
        <Reload_value v="0" />
        <Counter_period v="STOP" />
      </group>
      <group name="Interrupts">
        <Interrupt v="INT_SysTick" />
        <Interrupt_priority v="0 (Highest)" />
        <ISR_Name v="SysTick_Interrupt" />
        <Timer_interrupt v="Enabled" />
      </group>
      <group name="Initialization">
        <Timer_enable v="no" />
        <Clear_counter v="yes" />
        <Call_Init_method v="no" />
      </group>
    </Properties>
    <Methods>
      <Init v="generate code" />
    </Methods>
    <Events>
      <EmptySection_DummyValue />
    </Events>
  </Bean>
  <Bean name="BitIO_AD_NOT_RESET0" type="BitIO_LDD">
    <Enabled v="Y" />
    <Properties>
      <Component_name v="BitIO_AD_NOT_RESET0" />
      <Pin_for_I_O v="PTE0/UART1_TX/RTC_CLKOUT/CMP0_OUT/I2C1_SDA" />
      <Pin_signal v="AD_NOT_RESET" />
      <Direction v="Output" />
      <group name="Initialization">
        <Init__direction v="Output" />
        <Init__value v="1" />
        <Auto_initialization v="no" />
      </group>
      <Safe_mode v="no" />
    </Properties>
    <Methods>
      <Init v="generate code" />
      <Deinit v="don&amp;apos;t generate code" />
      <GetDir v="don&amp;apos;t generate code" />
      <SetDir v="don&amp;apos;t generate code" />
      <SetInput v="don&amp;apos;t generate code" />
      <SetOutput v="don&amp;apos;t generate code" />
      <GetVal v="generate code" />
      <PutVal v="generate code" />
      <ClrVal v="generate code" />
      <SetVal v="generate code" />
      <NegVal v="don&amp;apos;t generate code" />
      <ConnectPin v="don&amp;apos;t generate code" />
      <GetRawVal v="don&amp;apos;t generate code" />
    </Methods>
    <Events>
      <EmptySection_DummyValue />
    </Events>
  </Bean>
  <Bean name="BitIO_PTB0_NOT_DRDY" type="BitIO_LDD">
    <Enabled v="N" />
    <Properties>
      <Component_name v="BitIO_PTB0_NOT_DRDY" />
      <Pin_for_I_O v="ADC0_SE8/TSI0_CH0/PTB0/LLWU_P5/I2C0_SCL/TPM1_CH0" />
      <Pin_signal v="NOT_DRDY" />
      <Direction v="Input" />
      <group name="Initialization">
        <Init__direction v="Input" />
        <Init__value v="0" />
        <Auto_initialization v="no" />
      </group>
      <Safe_mode v="no" />
    </Properties>
    <Methods>
      <Init v="generate code" />
      <Deinit v="don&amp;apos;t generate code" />
      <GetDir v="don&amp;apos;t generate code" />
      <SetDir v="don&amp;apos;t generate code" />
      <SetInput v="don&amp;apos;t generate code" />
      <SetOutput v="don&amp;apos;t generate code" />
      <GetVal v="generate code" />
      <PutVal v="don&amp;apos;t generate code" />
      <ClrVal v="don&amp;apos;t generate code" />
      <SetVal v="don&amp;apos;t generate code" />
      <NegVal v="don&amp;apos;t generate code" />
      <ConnectPin v="don&amp;apos;t generate code" />
      <GetRawVal v="don&amp;apos;t generate code" />
    </Methods>
    <Events>
      <EmptySection_DummyValue />
    </Events>
  </Bean>
  <Bean name="BitIO_AD_START0" type="BitIO_LDD">
    <Enabled v="Y" />
    <Properties>
      <Component_name v="BitIO_AD_START0" />
      <Pin_for_I_O v="ADC0_SE12/TSI0_CH7/PTB2/I2C0_SCL/TPM2_CH0" />
      <Pin_signal v="AD_START" />
      <Direction v="Output" />
      <group name="Initialization">
        <Init__direction v="Output" />
        <Init__value v="0" />
        <Auto_initialization v="no" />
      </group>
      <Safe_mode v="no" />
    </Properties>
    <Methods>
      <Init v="generate code" />
      <Deinit v="don&amp;apos;t generate code" />
      <GetDir v="don&amp;apos;t generate code" />
      <SetDir v="don&amp;apos;t generate code" />
      <SetInput v="don&amp;apos;t generate code" />
      <SetOutput v="don&amp;apos;t generate code" />
      <GetVal v="generate code" />
      <PutVal v="generate code" />
      <ClrVal v="generate code" />
      <SetVal v="generate code" />
      <NegVal v="don&amp;apos;t generate code" />
      <ConnectPin v="don&amp;apos;t generate code" />
      <GetRawVal v="don&amp;apos;t generate code" />
    </Methods>
    <Events>
      <EmptySection_DummyValue />
    </Events>
  </Bean>
  <Bean name="BitIO_UPRDY" type="BitIO_LDD">
    <Enabled v="Y" />
    <Properties>
      <Component_name v="BitIO_UPRDY" />
      <Pin_for_I_O v="CMP0_IN5/ADC0_SE4b/PTE29/TPM0_CH2/TPM_CLKIN0" />
      <Pin_signal v="BitIO_UPRDY" />
      <Direction v="Output" />
      <group name="Initialization">
        <Init__direction v="Output" />
        <Init__value v="1" />
        <Auto_initialization v="no" />
      </group>
      <Safe_mode v="no" />
    </Properties>
    <Methods>
      <Init v="generate code" />
      <Deinit v="don&amp;apos;t generate code" />
      <GetDir v="don&amp;apos;t generate code" />
      <SetDir v="don&amp;apos;t generate code" />
      <SetInput v="don&amp;apos;t generate code" />
      <SetOutput v="don&amp;apos;t generate code" />
      <GetVal v="generate code" />
      <PutVal v="generate code" />
      <ClrVal v="generate code" />
      <SetVal v="generate code" />
      <NegVal v="don&amp;apos;t generate code" />
      <ConnectPin v="don&amp;apos;t generate code" />
      <GetRawVal v="don&amp;apos;t generate code" />
    </Methods>
    <Events>
      <EmptySection_DummyValue />
    </Events>
  </Bean>
  <Bean name="BitIO_PTD4_NOT_DRDY" type="BitIO_LDD">
    <Enabled v="N" />
    <Properties>
      <Component_name v="BitIO_PTD4_NOT_DRDY" />
      <Pin_for_I_O v="PTD4/LLWU_P14/SPI1_PCS0/UART2_RX/TPM0_CH4" />
      <Pin_signal v="NOT_DRDY" />
      <Direction v="Input" />
      <group name="Initialization">
        <Init__direction v="Input" />
        <Init__value v="0" />
        <Auto_initialization v="no" />
      </group>
      <Safe_mode v="no" />
    </Properties>
    <Methods>
      <Init v="generate code" />
      <Deinit v="don&amp;apos;t generate code" />
      <GetDir v="don&amp;apos;t generate code" />
      <SetDir v="don&amp;apos;t generate code" />
      <SetInput v="don&amp;apos;t generate code" />
      <SetOutput v="don&amp;apos;t generate code" />
      <GetVal v="generate code" />
      <PutVal v="don&amp;apos;t generate code" />
      <ClrVal v="don&amp;apos;t generate code" />
      <SetVal v="don&amp;apos;t generate code" />
      <NegVal v="don&amp;apos;t generate code" />
      <ConnectPin v="don&amp;apos;t generate code" />
      <GetRawVal v="don&amp;apos;t generate code" />
    </Methods>
    <Events>
      <EmptySection_DummyValue />
    </Events>
  </Bean>
  <Bean name="BitIO_AD_NOT_CS0" type="BitIO_LDD">
    <Enabled v="Y" />
    <Properties>
      <Component_name v="BitIO_AD_NOT_CS0" />
      <Pin_for_I_O v="PTC4/LLWU_P8/SPI0_PCS0/UART1_TX/TPM0_CH3" />
      <Pin_signal v="AD_NOT_CS0" />
      <Direction v="Output" />
      <group name="Initialization">
        <Init__direction v="Output" />
        <Init__value v="1" />
        <Auto_initialization v="no" />
      </group>
      <Safe_mode v="no" />
    </Properties>
    <Methods>
      <Init v="generate code" />
      <Deinit v="don&amp;apos;t generate code" />
      <GetDir v="don&amp;apos;t generate code" />
      <SetDir v="don&amp;apos;t generate code" />
      <SetInput v="don&amp;apos;t generate code" />
      <SetOutput v="don&amp;apos;t generate code" />
      <GetVal v="generate code" />
      <PutVal v="generate code" />
      <ClrVal v="generate code" />
      <SetVal v="generate code" />
      <NegVal v="don&amp;apos;t generate code" />
      <ConnectPin v="don&amp;apos;t generate code" />
      <GetRawVal v="don&amp;apos;t generate code" />
    </Methods>
    <Events>
      <EmptySection_DummyValue />
    </Events>
  </Bean>
  <Bean name="EINT_AD_NOT_DRDY0" type="ExtInt_LDD">
    <Enabled v="Y" />
    <Properties>
      <Component_name v="EINT_AD_NOT_DRDY0" />
      <Pin v="TSI0_CH2/PTA1/UART0_RX/TPM2_CH0" />
      <Pin_signal v="AD_NOT_DRDY0" />
      <Generate_interrupt_on v="falling edge" />
      <Interrupt v="INT_PORTA" />
      <Interrupt_priority v="medium priority" />
      <group name="Initialization">
        <Enabled_in_init__code v="no" />
        <list name="Auto Initialization" v="1">
          <Auto_initialization v="no" />
        </list>
      </group>
    </Properties>
    <Methods>
      <Init v="generate code" />
      <Deinit v="don&amp;apos;t generate code" />
      <Enable v="generate code" />
      <Disable v="generate code" />
      <GetVal v="don&amp;apos;t generate code" />
      <SetEdge v="don&amp;apos;t generate code" />
      <SetOperationMode v="don&amp;apos;t generate code" />
      <GetDriverState v="don&amp;apos;t generate code" />
      <ConnectPin v="don&amp;apos;t generate code" />
    </Methods>
    <Events>
      <Event_module_name v="Events" />
      <event name="OnInterrupt" v="generate code">
        <Event_procedure_name v="EINT_AD_NOT_DRDY0_OnInterrupt" />
      </event>
    </Events>
  </Bean>
  <Bean name="EINT_SYNC_INT" type="ExtInt_LDD">
    <Enabled v="Y" />
    <Properties>
      <Component_name v="EINT_SYNC_INT" />
      <Pin v="TSI0_CH3/PTA2/UART0_TX/TPM2_CH1" />
      <Pin_signal v="SYNC_INT" />
      <Generate_interrupt_on v="both edges" />
      <Interrupt v="INT_PORTA" />
      <Interrupt_priority v="medium priority" />
      <group name="Initialization">
        <Enabled_in_init__code v="no" />
        <list name="Auto Initialization" v="1">
          <Auto_initialization v="no" />
        </list>
      </group>
    </Properties>
    <Methods>
      <Init v="generate code" />
      <Deinit v="don&amp;apos;t generate code" />
      <Enable v="generate code" />
      <Disable v="generate code" />
      <GetVal v="don&amp;apos;t generate code" />
      <SetEdge v="don&amp;apos;t generate code" />
      <SetOperationMode v="don&amp;apos;t generate code" />
      <GetDriverState v="don&amp;apos;t generate code" />
      <ConnectPin v="don&amp;apos;t generate code" />
    </Methods>
    <Events>
      <Event_module_name v="Events" />
      <event name="OnInterrupt" v="generate code">
        <Event_procedure_name v="EINT_SYNC_INT_OnInterrupt" />
      </event>
    </Events>
  </Bean>
  <Bean name="BitIO_PTC3_TEST_SIGNAL" type="BitIO_LDD">
    <Enabled v="N" />
    <Properties>
      <Component_name v="BitIO_PTC3_TEST_SIGNAL" />
      <Pin_for_I_O v="PTC3/LLWU_P7/UART1_RX/TPM0_CH2/CLKOUTa" />
      <Pin_signal v="TEST_SIGNAL" />
      <Direction v="Input/Output" />
      <group name="Initialization">
        <Init__direction v="Output" />
        <Init__value v="0" />
        <Auto_initialization v="no" />
      </group>
      <Safe_mode v="no" />
    </Properties>
    <Methods>
      <Init v="generate code" />
      <Deinit v="don&amp;apos;t generate code" />
      <GetDir v="don&amp;apos;t generate code" />
      <SetDir v="generate code" />
      <SetInput v="generate code" />
      <SetOutput v="don&amp;apos;t generate code" />
      <GetVal v="generate code" />
      <PutVal v="generate code" />
      <ClrVal v="generate code" />
      <SetVal v="generate code" />
      <NegVal v="don&amp;apos;t generate code" />
      <ConnectPin v="don&amp;apos;t generate code" />
      <GetRawVal v="don&amp;apos;t generate code" />
    </Methods>
    <Events>
      <EmptySection_DummyValue />
    </Events>
  </Bean>
  <Bean name="DMAT_M_SPI_TX" type="DMATransfer_LDD">
    <Enabled v="Y" />
    <Properties>
      <Component_name v="DMAT_M_SPI_TX" />
      <DMA_controller_device v="DMA_CTRL" />
      <group name="Channel">
        <enumgroup name="Channel select" v="Fixed">
          <Channel v="DMA_Channel0" />
          <Interrupts v="Enabled" />
          <Allocate_channel v="yes" />
        </enumgroup>
      </group>
      <group name="Trigger">
        <enumgroup name="Trigger source type" v="Peripheral device">
          <Trigger_source v="SPI0_Transmit_DMA_Request" />
          <boolgroup name="Periodic trigger" v="Disabled" />
        </enumgroup>
      </group>
      <group name="Data source">
        <External_object_declaration v="volatile byte* SPI0TxDMADataSourceBuffer = NULL;" />
        <Address v="SPI0TxDMADataSourceBuffer" />
        <Transfer_size v="8-bit" />
        <Address_offset v="1" />
        <Circular_buffer v="Buffer disabled" />
      </group>
      <group name="Data destination">
        <External_object_declaration v="volatile byte* SPI0TxDMADataDestinationBuffer = NULL;" />
        <Address v="(&amp;amp;SPI0_D)" />
        <Transfer_size v="8-bit" />
        <Address_offset v="0" />
        <Circular_buffer v="Buffer disabled" />
      </group>
      <group name="Data size">
        <External_object_declaration v="volatile uint8_t SPI0TxDMAByteCount = 0;" />
        <Value v="SPI0TxDMAByteCount" />
      </group>
      <enumgroup name="Transfer control" v="Cycle-steal">
        <Disable_after_transfer v="yes" />
        <Asynchronous_requests v="Disabled" />
        <boolgroup name="Channel linking" v="Disabled" />
        <enumgroup name="After request complete" v="No action">
          <EmptySection_DummyValue />
        </enumgroup>
        <enumgroup name="After transfer complete" v="No action">
          <EmptySection_DummyValue />
        </enumgroup>
      </enumgroup>
      <group name="Initialization">
        <list name="Auto Initialization" v="1">
          <Auto_initialization v="no" />
        </list>
        <Half_complete v="Disabled" />
        <group name="Event mask">
          <OnComplete v="Enabled" />
          <OnError v="Enabled" />
        </group>
      </group>
    </Properties>
    <Methods>
      <Init v="generate code" />
      <Deinit v="generate code" />
      <SetEventMask v="don&amp;apos;t generate code" />
      <GetEventMask v="don&amp;apos;t generate code" />
      <AllocateChannel v="generate code" />
      <FreeChannel v="don&amp;apos;t generate code" />
      <EnableChannel v="generate code" />
      <DisableChannel v="generate code" />
      <StartTransfer v="don&amp;apos;t generate code" />
      <CancelTransfer v="don&amp;apos;t generate code" />
      <GetTransferredBytes v="don&amp;apos;t generate code" />
      <GetChannelStatus v="don&amp;apos;t generate code" />
      <GetLastError v="don&amp;apos;t generate code" />
      <SetSourceAddress v="generate code" />
      <SetDestinationAddress v="generate code" />
      <SetSourceTransferSize v="don&amp;apos;t generate code" />
      <SetDestinationTransferSize v="don&amp;apos;t generate code" />
      <SetByteCount v="generate code" />
      <SetTransferCount v="don&amp;apos;t generate code" />
      <SetDescriptorUpdate v="don&amp;apos;t generate code" />
      <GetDescriptorUpdate v="don&amp;apos;t generate code" />
    </Methods>
    <Events>
      <Event_module_name v="Events" />
      <event name="OnComplete" v="generate code">
        <Event_procedure_name v="DMAT_M_SPI_TX_OnComplete" />
      </event>
      <event name="OnError" v="generate code">
        <Event_procedure_name v="DMAT_M_SPI_TX_OnError" />
      </event>
    </Events>
  </Bean>
  <Bean name="DMA_CTRL" type="DMA_LDD">
    <Enabled v="Y" />
    <Properties>
      <Component_name v="DMA_CTRL" />
      <Device v="DMA" />
      <boolgroup name="Channel arbitration type" v="Round robin" />
      <list name="DMA channels" v="4">
        <group name="Settings of DMA channel ">
          <Channel v="DMA_Channel0" />
          <boolgroup name="Channel arbitration type" v="Round robin" />
          <boolgroup name="Interrupt service" v="Enabled">
            <Transfer_complete_interrupt v="INT_DMA0" />
            <Transfer_complete_interrupt_priority v="high priority" />
          </boolgroup>
        </group>
        <group name="Settings of DMA channel ">
          <Channel v="DMA_Channel1" />
          <boolgroup name="Channel arbitration type" v="Round robin" />
          <boolgroup name="Interrupt service" v="Enabled">
            <Transfer_complete_interrupt v="INT_DMA1" />
            <Transfer_complete_interrupt_priority v="high priority" />
          </boolgroup>
        </group>
        <group name="Settings of DMA channel ">
          <Channel v="DMA_Channel2" />
          <boolgroup name="Channel arbitration type" v="Round robin" />
          <boolgroup name="Interrupt service" v="Enabled">
            <Transfer_complete_interrupt v="INT_DMA2" />
            <Transfer_complete_interrupt_priority v="low priority" />
          </boolgroup>
        </group>
        <group name="Settings of DMA channel ">
          <Channel v="DMA_Channel3" />
          <boolgroup name="Channel arbitration type" v="Round robin" />
          <boolgroup name="Interrupt service" v="Enabled">
            <Transfer_complete_interrupt v="INT_DMA3" />
            <Transfer_complete_interrupt_priority v="low priority" />
          </boolgroup>
        </group>
      </list>
      <group name="Initialization">
        <Enabled_in_init__code v="no" />
        <list name="Auto Initialization" v="1">
          <Auto_initialization v="no" />
        </list>
      </group>
      <list name="CPU clock/configuration selection (included)" v="1">
        <group name="CPU clock/configuration selection">
          <Clock_configuration_0 v="This component enabled" />
          <Clock_configuration_1 v="This component disabled" />
          <Clock_configuration_2 v="This component disabled" />
          <Clock_configuration_3 v="This component disabled" />
          <Clock_configuration_4 v="This component disabled" />
          <Clock_configuration_5 v="This component disabled" />
          <Clock_configuration_6 v="This component disabled" />
          <Clock_configuration_7 v="This component disabled" />
        </group>
      </list>
    </Properties>
    <Methods>
      <Init v="generate code" />
      <Deinit v="generate code" />
      <Enable v="generate code" />
      <Disable v="generate code" />
      <SetEventMask v="don&amp;apos;t generate code" />
      <GetEventMask v="don&amp;apos;t generate code" />
      <AllocateChannel v="generate code" />
      <FreeChannel v="don&amp;apos;t generate code" />
      <EnableChannel v="generate code" />
      <DisableChannel v="generate code" />
      <StartChannelTransfer v="don&amp;apos;t generate code" />
      <CancelChannelTransfer v="don&amp;apos;t generate code" />
      <GetChannelTransferredBytes v="don&amp;apos;t generate code" />
      <GetChannelStatus v="don&amp;apos;t generate code" />
      <GetChannelLastError v="don&amp;apos;t generate code" />
      <SetChannelSourceAddress v="generate code" />
      <SetChannelDestinationAddress v="generate code" />
      <SetChannelSourceTransferSize v="don&amp;apos;t generate code" />
      <SetChannelDestinationTransferSize v="don&amp;apos;t generate code" />
      <SetChannelByteCount v="generate code" />
      <SetChannelTransferCount v="don&amp;apos;t generate code" />
      <GetChannelDescriptorUpdate v="don&amp;apos;t generate code" />
      <SetChannelDescriptorUpdate v="don&amp;apos;t generate code" />
      <SetOperationMode v="don&amp;apos;t generate code" />
      <GetDriverState v="don&amp;apos;t generate code" />
    </Methods>
    <Events>
      <EmptySection_DummyValue />
    </Events>
  </Bean>
  <Bean name="DMAT_M_SPI_RX" type="DMATransfer_LDD">
    <Enabled v="Y" />
    <Properties>
      <Component_name v="DMAT_M_SPI_RX" />
      <DMA_controller_device v="DMA_CTRL" />
      <group name="Channel">
        <enumgroup name="Channel select" v="Fixed">
          <Channel v="DMA_Channel1" />
          <Interrupts v="Enabled" />
          <Allocate_channel v="yes" />
        </enumgroup>
      </group>
      <group name="Trigger">
        <enumgroup name="Trigger source type" v="Peripheral device">
          <Trigger_source v="SPI0_Receive_DMA_Request" />
          <boolgroup name="Periodic trigger" v="Disabled" />
        </enumgroup>
      </group>
      <group name="Data source">
        <External_object_declaration v="volatile byte* SPI0RxDMADataSourceBuffer = NULL;" />
        <Address v="(&amp;amp;SPI0_D)" />
        <Transfer_size v="8-bit" />
        <Address_offset v="0" />
        <Circular_buffer v="Buffer disabled" />
      </group>
      <group name="Data destination">
        <External_object_declaration v="volatile byte* SPI0RxDMADataDestinationBuffer = NULL;" />
        <Address v="SPI0RxDMADataDestinationBuffer" />
        <Transfer_size v="8-bit" />
        <Address_offset v="1" />
        <Circular_buffer v="Buffer disabled" />
      </group>
      <group name="Data size">
        <External_object_declaration v="volatile uint8_t SPI0RxDMAByteCount = 0;" />
        <Value v="SPI0RxDMAByteCount" />
      </group>
      <enumgroup name="Transfer control" v="Cycle-steal">
        <Disable_after_transfer v="yes" />
        <Asynchronous_requests v="Disabled" />
        <boolgroup name="Channel linking" v="Disabled" />
        <enumgroup name="After request complete" v="No action">
          <EmptySection_DummyValue />
        </enumgroup>
        <enumgroup name="After transfer complete" v="No action">
          <EmptySection_DummyValue />
        </enumgroup>
      </enumgroup>
      <group name="Initialization">
        <list name="Auto Initialization" v="1">
          <Auto_initialization v="no" />
        </list>
        <Half_complete v="Disabled" />
        <group name="Event mask">
          <OnComplete v="Enabled" />
          <OnError v="Enabled" />
        </group>
      </group>
    </Properties>
    <Methods>
      <Init v="generate code" />
      <Deinit v="generate code" />
      <SetEventMask v="don&amp;apos;t generate code" />
      <GetEventMask v="don&amp;apos;t generate code" />
      <AllocateChannel v="generate code" />
      <FreeChannel v="don&amp;apos;t generate code" />
      <EnableChannel v="generate code" />
      <DisableChannel v="generate code" />
      <StartTransfer v="don&amp;apos;t generate code" />
      <CancelTransfer v="don&amp;apos;t generate code" />
      <GetTransferredBytes v="don&amp;apos;t generate code" />
      <GetChannelStatus v="don&amp;apos;t generate code" />
      <GetLastError v="don&amp;apos;t generate code" />
      <SetSourceAddress v="generate code" />
      <SetDestinationAddress v="generate code" />
      <SetSourceTransferSize v="don&amp;apos;t generate code" />
      <SetDestinationTransferSize v="don&amp;apos;t generate code" />
      <SetByteCount v="generate code" />
      <SetTransferCount v="don&amp;apos;t generate code" />
      <SetDescriptorUpdate v="don&amp;apos;t generate code" />
      <GetDescriptorUpdate v="don&amp;apos;t generate code" />
    </Methods>
    <Events>
      <Event_module_name v="Events" />
      <event name="OnComplete" v="generate code">
        <Event_procedure_name v="DMAT_M_SPI_RX_OnComplete" />
      </event>
      <event name="OnError" v="generate code">
        <Event_procedure_name v="DMAT_M_SPI_RX_OnError" />
      </event>
    </Events>
  </Bean>
  <Bean name="DMAT_S_SPI_TX" type="DMATransfer_LDD">
    <Enabled v="Y" />
    <Properties>
      <Component_name v="DMAT_S_SPI_TX" />
      <DMA_controller_device v="DMA_CTRL" />
      <group name="Channel">
        <enumgroup name="Channel select" v="Fixed">
          <Channel v="DMA_Channel2" />
          <Interrupts v="Enabled" />
          <Allocate_channel v="yes" />
        </enumgroup>
      </group>
      <group name="Trigger">
        <enumgroup name="Trigger source type" v="Peripheral device">
          <Trigger_source v="SPI1_Transmit_DMA_Request" />
          <boolgroup name="Periodic trigger" v="Disabled" />
        </enumgroup>
      </group>
      <group name="Data source">
        <External_object_declaration v="volatile byte* SPI1TxDMADataSourceBuffer = NULL;" />
        <Address v="SPI1TxDMADataSourceBuffer" />
        <Transfer_size v="8-bit" />
        <Address_offset v="1" />
        <Circular_buffer v="Buffer disabled" />
      </group>
      <group name="Data destination">
        <External_object_declaration v="volatile byte* SPI1TxDMADataDestinationBuffer = NULL;" />
        <Address v="(&amp;amp;SPI1_D)" />
        <Transfer_size v="8-bit" />
        <Address_offset v="0" />
        <Circular_buffer v="Buffer disabled" />
      </group>
      <group name="Data size">
        <External_object_declaration v="volatile uint8_t SPI1TxDMAByteCount = 0;" />
        <Value v="SPI1TxDMAByteCount" />
      </group>
      <enumgroup name="Transfer control" v="Cycle-steal">
        <Disable_after_transfer v="yes" />
        <Asynchronous_requests v="Disabled" />
        <boolgroup name="Channel linking" v="Disabled" />
        <enumgroup name="After request complete" v="No action">
          <EmptySection_DummyValue />
        </enumgroup>
        <enumgroup name="After transfer complete" v="No action">
          <EmptySection_DummyValue />
        </enumgroup>
      </enumgroup>
      <group name="Initialization">
        <list name="Auto Initialization" v="1">
          <Auto_initialization v="no" />
        </list>
        <Half_complete v="Disabled" />
        <group name="Event mask">
          <OnComplete v="Enabled" />
          <OnError v="Enabled" />
        </group>
      </group>
    </Properties>
    <Methods>
      <Init v="generate code" />
      <Deinit v="generate code" />
      <SetEventMask v="don&amp;apos;t generate code" />
      <GetEventMask v="don&amp;apos;t generate code" />
      <AllocateChannel v="generate code" />
      <FreeChannel v="don&amp;apos;t generate code" />
      <EnableChannel v="generate code" />
      <DisableChannel v="generate code" />
      <StartTransfer v="don&amp;apos;t generate code" />
      <CancelTransfer v="don&amp;apos;t generate code" />
      <GetTransferredBytes v="don&amp;apos;t generate code" />
      <GetChannelStatus v="don&amp;apos;t generate code" />
      <GetLastError v="don&amp;apos;t generate code" />
      <SetSourceAddress v="generate code" />
      <SetDestinationAddress v="generate code" />
      <SetSourceTransferSize v="don&amp;apos;t generate code" />
      <SetDestinationTransferSize v="don&amp;apos;t generate code" />
      <SetByteCount v="generate code" />
      <SetTransferCount v="don&amp;apos;t generate code" />
      <SetDescriptorUpdate v="don&amp;apos;t generate code" />
      <GetDescriptorUpdate v="don&amp;apos;t generate code" />
    </Methods>
    <Events>
      <Event_module_name v="Events" />
      <event name="OnComplete" v="generate code">
        <Event_procedure_name v="DMAT_S_SPI_TX_OnComplete" />
      </event>
      <event name="OnError" v="generate code">
        <Event_procedure_name v="DMAT_S_SPI_TX_OnError" />
      </event>
    </Events>
  </Bean>
  <Bean name="DMAT_S_SPI_RX" type="DMATransfer_LDD">
    <Enabled v="Y" />
    <Properties>
      <Component_name v="DMAT_S_SPI_RX" />
      <DMA_controller_device v="DMA_CTRL" />
      <group name="Channel">
        <enumgroup name="Channel select" v="Fixed">
          <Channel v="DMA_Channel3" />
          <Interrupts v="Enabled" />
          <Allocate_channel v="yes" />
        </enumgroup>
      </group>
      <group name="Trigger">
        <enumgroup name="Trigger source type" v="Peripheral device">
          <Trigger_source v="SPI1_Receive_DMA_Request" />
          <boolgroup name="Periodic trigger" v="Disabled" />
        </enumgroup>
      </group>
      <group name="Data source">
        <External_object_declaration v="volatile byte* SPI1RxDMADataSourceBuffer = NULL;" />
        <Address v="(&amp;amp;SPI1_D)" />
        <Transfer_size v="8-bit" />
        <Address_offset v="0" />
        <Circular_buffer v="Buffer disabled" />
      </group>
      <group name="Data destination">
        <External_object_declaration v="volatile byte* SPI1RxDMADataDestinationBuffer = NULL;" />
        <Address v="SPI1RxDMADataDestinationBuffer" />
        <Transfer_size v="8-bit" />
        <Address_offset v="1" />
        <Circular_buffer v="Buffer disabled" />
      </group>
      <group name="Data size">
        <External_object_declaration v="volatile uint8_t SPI1RxDMAByteCount = 0;" />
        <Value v="SPI1RxDMAByteCount" />
      </group>
      <enumgroup name="Transfer control" v="Cycle-steal">
        <Disable_after_transfer v="yes" />
        <Asynchronous_requests v="Disabled" />
        <boolgroup name="Channel linking" v="Disabled" />
        <enumgroup name="After request complete" v="No action">
          <EmptySection_DummyValue />
        </enumgroup>
        <enumgroup name="After transfer complete" v="No action">
          <EmptySection_DummyValue />
        </enumgroup>
      </enumgroup>
      <group name="Initialization">
        <list name="Auto Initialization" v="1">
          <Auto_initialization v="no" />
        </list>
        <Half_complete v="Disabled" />
        <group name="Event mask">
          <OnComplete v="Enabled" />
          <OnError v="Enabled" />
        </group>
      </group>
    </Properties>
    <Methods>
      <Init v="generate code" />
      <Deinit v="generate code" />
      <SetEventMask v="don&amp;apos;t generate code" />
      <GetEventMask v="don&amp;apos;t generate code" />
      <AllocateChannel v="generate code" />
      <FreeChannel v="don&amp;apos;t generate code" />
      <EnableChannel v="generate code" />
      <DisableChannel v="generate code" />
      <StartTransfer v="don&amp;apos;t generate code" />
      <CancelTransfer v="don&amp;apos;t generate code" />
      <GetTransferredBytes v="don&amp;apos;t generate code" />
      <GetChannelStatus v="don&amp;apos;t generate code" />
      <GetLastError v="don&amp;apos;t generate code" />
      <SetSourceAddress v="generate code" />
      <SetDestinationAddress v="generate code" />
      <SetSourceTransferSize v="don&amp;apos;t generate code" />
      <SetDestinationTransferSize v="don&amp;apos;t generate code" />
      <SetByteCount v="generate code" />
      <SetTransferCount v="don&amp;apos;t generate code" />
      <SetDescriptorUpdate v="don&amp;apos;t generate code" />
      <GetDescriptorUpdate v="don&amp;apos;t generate code" />
    </Methods>
    <Events>
      <Event_module_name v="Events" />
      <event name="OnComplete" v="generate code">
        <Event_procedure_name v="DMAT_S_SPI_RX_OnComplete" />
      </event>
      <event name="OnError" v="generate code">
        <Event_procedure_name v="DMAT_S_SPI_RX_OnError" />
      </event>
    </Events>
  </Bean>
  <Bean name="BitIO_AD_NOT_CS1" type="BitIO_LDD">
    <Enabled v="Y" />
    <Properties>
      <Component_name v="BitIO_AD_NOT_CS1" />
      <Pin_for_I_O v="CMP0_IN2/PTC8/I2C0_SCL/TPM0_CH4" />
      <Pin_signal v="AD_NOT_CS1" />
      <Direction v="Output" />
      <group name="Initialization">
        <Init__direction v="Output" />
        <Init__value v="1" />
        <Auto_initialization v="no" />
      </group>
      <Safe_mode v="no" />
    </Properties>
    <Methods>
      <Init v="generate code" />
      <Deinit v="don&amp;apos;t generate code" />
      <GetDir v="don&amp;apos;t generate code" />
      <SetDir v="don&amp;apos;t generate code" />
      <SetInput v="don&amp;apos;t generate code" />
      <SetOutput v="don&amp;apos;t generate code" />
      <GetVal v="generate code" />
      <PutVal v="generate code" />
      <ClrVal v="generate code" />
      <SetVal v="generate code" />
      <NegVal v="don&amp;apos;t generate code" />
      <ConnectPin v="don&amp;apos;t generate code" />
      <GetRawVal v="don&amp;apos;t generate code" />
    </Methods>
    <Events>
      <EmptySection_DummyValue />
    </Events>
  </Bean>
  <Bean name="BitIO_AD_NOT_RESET1" type="BitIO_LDD">
    <Enabled v="Y" />
    <Properties>
      <Component_name v="BitIO_AD_NOT_RESET1" />
      <Pin_for_I_O v="PTE1/SPI1_MOSI/UART1_RX/SPI1_MISO/I2C1_SCL" />
      <Pin_signal v="AD_NOT_RESET1" />
      <Direction v="Output" />
      <group name="Initialization">
        <Init__direction v="Output" />
        <Init__value v="1" />
        <Auto_initialization v="no" />
      </group>
      <Safe_mode v="no" />
    </Properties>
    <Methods>
      <Init v="generate code" />
      <Deinit v="don&amp;apos;t generate code" />
      <GetDir v="don&amp;apos;t generate code" />
      <SetDir v="don&amp;apos;t generate code" />
      <SetInput v="don&amp;apos;t generate code" />
      <SetOutput v="don&amp;apos;t generate code" />
      <GetVal v="generate code" />
      <PutVal v="generate code" />
      <ClrVal v="generate code" />
      <SetVal v="generate code" />
      <NegVal v="don&amp;apos;t generate code" />
      <ConnectPin v="don&amp;apos;t generate code" />
      <GetRawVal v="don&amp;apos;t generate code" />
    </Methods>
    <Events>
      <EmptySection_DummyValue />
    </Events>
  </Bean>
  <Bean name="BitIO_AD_START1" type="BitIO_LDD">
    <Enabled v="N" />
    <Properties>
      <Component_name v="BitIO_AD_START1" />
      <Pin_for_I_O v="ADC0_SE9/TSI0_CH6/PTB1/I2C0_SDA/TPM1_CH1" />
      <Pin_signal v="AD_START1" />
      <Direction v="Output" />
      <group name="Initialization">
        <Init__direction v="Output" />
        <Init__value v="0" />
        <Auto_initialization v="no" />
      </group>
      <Safe_mode v="no" />
    </Properties>
    <Methods>
      <Init v="generate code" />
      <Deinit v="don&amp;apos;t generate code" />
      <GetDir v="don&amp;apos;t generate code" />
      <SetDir v="don&amp;apos;t generate code" />
      <SetInput v="don&amp;apos;t generate code" />
      <SetOutput v="don&amp;apos;t generate code" />
      <GetVal v="generate code" />
      <PutVal v="generate code" />
      <ClrVal v="generate code" />
      <SetVal v="generate code" />
      <NegVal v="don&amp;apos;t generate code" />
      <ConnectPin v="don&amp;apos;t generate code" />
      <GetRawVal v="don&amp;apos;t generate code" />
    </Methods>
    <Events>
      <EmptySection_DummyValue />
    </Events>
  </Bean>
  <Bean name="EINT_AD_NOT_DRDY1" type="ExtInt_LDD">
    <Enabled v="N" />
    <Properties>
      <Component_name v="EINT_AD_NOT_DRDY1" />
      <Pin v="PTA5/USB_CLKIN/TPM0_CH2" />
      <Pin_signal v="AD_NOT_DRDY1" />
      <Generate_interrupt_on v="falling edge" />
      <Interrupt v="INT_PORTA" />
      <Interrupt_priority v="medium priority" />
      <group name="Initialization">
        <Enabled_in_init__code v="no" />
        <list name="Auto Initialization" v="1">
          <Auto_initialization v="no" />
        </list>
      </group>
    </Properties>
    <Methods>
      <Init v="generate code" />
      <Deinit v="don&amp;apos;t generate code" />
      <Enable v="generate code" />
      <Disable v="generate code" />
      <GetVal v="don&amp;apos;t generate code" />
      <SetEdge v="don&amp;apos;t generate code" />
      <SetOperationMode v="don&amp;apos;t generate code" />
      <GetDriverState v="don&amp;apos;t generate code" />
      <ConnectPin v="don&amp;apos;t generate code" />
    </Methods>
    <Events>
      <Event_module_name v="Events" />
      <event name="OnInterrupt" v="generate code">
        <Event_procedure_name v="EINT_AD_NOT_DRDY1_OnInterrupt" />
      </event>
    </Events>
  </Bean>
</PE_PROJECT_SETTINGS_DOCUMENTATION>

